dypylib/__init__.py
dypylib/_version.py
dypylib/bio/__init__.py
dypylib/bio/base.py
dypylib/bio/seq/Annotation.bk-to-del.py
dypylib/bio/seq/Annotation.py
dypylib/bio/seq/Annotation_raw.py
dypylib/bio/seq/__init__.py
dypylib/bio/seq/base.py
dypylib/bio/seq/countgtf.py
dypylib/bio/seq/gtf2stat.py
dypylib/bio/seq/gtf2table.py
dypylib/bio/seq/ncbi_chr.py
dypylib/bio/seq/plotsts.py
dypylib/bio/seq/tmp.py
dypylib/bio/seq/format/Fasta.py
dypylib/bio/seq/format/__init__.py
dypylib/bio/seq/format/gbParser.py
dypylib/bio/seq/format/generalParser.py
dypylib/bio/seq/format/merge_overlap_gene.py
dypylib/bio/seq/format/rename_gtf_id.py
dypylib/pylib/__init__.py
dypylib/pylib/case_insensitive_dict.py
dypylib-0.0.6.3.data/scripts/annot_from_file.py
dypylib-0.0.6.3.data/scripts/countgtf.py
dypylib-0.0.6.3.data/scripts/filter.py
dypylib-0.0.6.3.data/scripts/gtf2stat.py
dypylib-0.0.6.3.data/scripts/gtf2table.py
dypylib-0.0.6.3.data/scripts/merge_overlap_gene.py
dypylib-0.0.6.3.data/scripts/ncbi_chr.py
dypylib-0.0.6.3.data/scripts/plotsts.py
dypylib-0.0.6.3.data/scripts/subset_fasta.py
dypylib-0.0.6.3.data/scripts/subset_fastq.py
dypylib-0.0.6.3.dist-info/LICENSE
dypylib-0.0.6.3.dist-info/METADATA
dypylib-0.0.6.3.dist-info/WHEEL
dypylib-0.0.6.3.dist-info/top_level.txt
dypylib-0.0.6.3.dist-info/RECORD
