Metadata-Version: 2.1
Name: dypylib
Version: 0.0.6.3
Summary: genomics research
Home-page: https://github.com/yduanBioinfo/dypylib
Author: You Duan
Author-email: duanyou@outlook.com
License: UNKNOWN
Platform: UNKNOWN
Classifier: Programming Language :: Python :: 3
Classifier: License :: OSI Approved :: GNU General Public License v3 (GPLv3)
Classifier: Operating System :: OS Independent
Requires-Python: >=3.6
License-File: LICENSE
Requires-Dist: case-insensitive-dictionary
